{
  "version": "1.0",
  "agentName": "DocumentationAgent",
  "createdAt": "2025-12-12T21:41:01.480Z",
  "patterns": [
    {
      "id": "pattern_1765575661523",
      "timestamp": "2025-12-12T21:41:01.523Z",
      "requirementName": "Test Project API",
      "name": "documentation-generation",
      "category": "generic-pattern",
      "description": "Generated documentation for 50 endpoints with guides and examples",
      "successRate": 0.8
    },
    {
      "id": "pattern_1765575819733",
      "timestamp": "2025-12-12T21:43:39.733Z",
      "requirementName": "unknown",
      "name": "documentation-generation",
      "category": "generic-pattern",
      "description": "Generated documentation for 50 endpoints with guides and examples",
      "successRate": 0.8
    },
    {
      "id": "pattern_1765576155683",
      "timestamp": "2025-12-12T21:49:15.683Z",
      "requirementName": "unknown",
      "name": "documentation-generation",
      "category": "generic-pattern",
      "description": "Generated documentation for 50 endpoints with guides and examples",
      "successRate": 0.8
    },
    {
      "id": "pattern_1765576573326",
      "timestamp": "2025-12-12T21:56:13.326Z",
      "requirementName": "Test Project API",
      "name": "documentation-generation",
      "category": "generic-pattern",
      "description": "Generated documentation for 50 endpoints with guides and examples",
      "successRate": 0.8
    },
    {
      "id": "pattern_1765576643316",
      "timestamp": "2025-12-12T21:57:23.316Z",
      "requirementName": "Test Project API",
      "name": "documentation-generation",
      "category": "generic-pattern",
      "description": "Generated documentation for 50 endpoints with guides and examples",
      "successRate": 0.8
    },
    {
      "id": "pattern_1765576682529",
      "timestamp": "2025-12-12T21:58:02.529Z",
      "requirementName": "Test Project API",
      "name": "documentation-generation",
      "category": "generic-pattern",
      "description": "Generated documentation for 50 endpoints with guides and examples",
      "successRate": 0.8
    },
    {
      "id": "pattern_1765577100311",
      "timestamp": "2025-12-12T22:05:00.311Z",
      "requirementName": "Test Project API",
      "name": "documentation-generation",
      "category": "generic-pattern",
      "description": "Generated documentation for 50 endpoints with guides and examples",
      "successRate": 0.8
    },
    {
      "id": "pattern_1765577239617",
      "timestamp": "2025-12-12T22:07:19.617Z",
      "requirementName": "Test Project API",
      "name": "documentation-generation",
      "category": "generic-pattern",
      "description": "Generated documentation for 50 endpoints with guides and examples",
      "successRate": 0.8
    },
    {
      "id": "pattern_1765577469247",
      "timestamp": "2025-12-12T22:11:09.247Z",
      "requirementName": "hello-world",
      "name": "documentation-generation",
      "category": "generic-pattern",
      "description": "Generated documentation for 94 endpoints with guides and examples",
      "successRate": 0.8
    },
    {
      "id": "pattern_1765578503299",
      "timestamp": "2025-12-12T22:28:23.299Z",
      "requirementName": "hello-world-feature-2",
      "name": "documentation-generation",
      "category": "generic-pattern",
      "description": "Generated documentation for 85 endpoints with guides and examples",
      "successRate": 0.8
    },
    {
      "id": "pattern_1765578542489",
      "timestamp": "2025-12-12T22:29:02.489Z",
      "requirementName": "hello-world-feature-2",
      "name": "documentation-generation",
      "category": "generic-pattern",
      "description": "Generated documentation for 85 endpoints with guides and examples",
      "successRate": 0.8
    },
    {
      "id": "pattern_1765578591610",
      "timestamp": "2025-12-12T22:29:51.610Z",
      "requirementName": "hello-world-feature-2",
      "name": "documentation-generation",
      "category": "generic-pattern",
      "description": "Generated documentation for 85 endpoints with guides and examples",
      "successRate": 0.8
    },
    {
      "id": "pattern_1765578641246",
      "timestamp": "2025-12-12T22:30:41.246Z",
      "requirementName": "hello-world-feature-2",
      "name": "documentation-generation",
      "category": "generic-pattern",
      "description": "Generated documentation for 85 endpoints with guides and examples",
      "successRate": 0.8
    },
    {
      "id": "pattern_1765579117344",
      "timestamp": "2025-12-12T22:38:37.344Z",
      "requirementName": "hello-world-feature-2",
      "name": "documentation-generation",
      "category": "generic-pattern",
      "description": "Generated documentation for 85 endpoints with guides and examples",
      "successRate": 0.8
    }
  ],
  "strategies": []
}